litk_mcp/__init__.py
litk_mcp-0.1.0.dist-info/METADATA
litk_mcp-0.1.0.dist-info/WHEEL
litk_mcp-0.1.0.dist-info/entry_points.txt
litk_mcp-0.1.0.dist-info/RECORD
