Metadata-Version: 2.4
Name: litk-mcp
Version: 0.1.0
Summary: Add your description here
Requires-Python: >=3.11
Requires-Dist: mcp[cli]>=1.13.1
